scripts/__init__.py
scripts/bootstrap.py
scripts/sfx_py_trace.py
scripts/site_/__init__.py
scripts/site_/sitecustomize.py
signalfx_tracing/__init__.py
signalfx_tracing/constants.py
signalfx_tracing/instrumentation.py
signalfx_tracing/patch_span.py
signalfx_tracing/tags.py
signalfx_tracing/utils.py
signalfx_tracing/version.py
signalfx_tracing/libraries/__init__.py
signalfx_tracing/libraries/celery_/__init__.py
signalfx_tracing/libraries/celery_/instrument.py
signalfx_tracing/libraries/django_/__init__.py
signalfx_tracing/libraries/django_/apps.py
signalfx_tracing/libraries/django_/instrument.py
signalfx_tracing/libraries/elasticsearch_/__init__.py
signalfx_tracing/libraries/elasticsearch_/instrument.py
signalfx_tracing/libraries/falcon_/__init__.py
signalfx_tracing/libraries/falcon_/instrument.py
signalfx_tracing/libraries/falcon_/middleware.py
signalfx_tracing/libraries/flask_/__init__.py
signalfx_tracing/libraries/flask_/instrument.py
signalfx_tracing/libraries/logging_/__init__.py
signalfx_tracing/libraries/logging_/instrument.py
signalfx_tracing/libraries/psycopg2_/__init__.py
signalfx_tracing/libraries/psycopg2_/instrument.py
signalfx_tracing/libraries/pymongo_/__init__.py
signalfx_tracing/libraries/pymongo_/instrument.py
signalfx_tracing/libraries/pymysql_/__init__.py
signalfx_tracing/libraries/pymysql_/instrument.py
signalfx_tracing/libraries/redis_/__init__.py
signalfx_tracing/libraries/redis_/instrument.py
signalfx_tracing/libraries/requests_/__init__.py
signalfx_tracing/libraries/requests_/instrument.py
signalfx_tracing/libraries/tornado_/__init__.py
signalfx_tracing/libraries/tornado_/instrument.py
tests/__init__.py
tests/utils.py
tests/integration/__init__.py
tests/integration/sitecustomize.py
tests/integration/test_jaeger_client.py
tests/integration/test_runner.py
tests/integration/django_/__init__.py
tests/integration/django_/conftest.py
tests/integration/django_/manage.py
tests/integration/django_/test_installed_app.py
signalfx_tracing-2.2.0.dist-info/LICENSE
signalfx_tracing-2.2.0.dist-info/METADATA
signalfx_tracing-2.2.0.dist-info/WHEEL
signalfx_tracing-2.2.0.dist-info/entry_points.txt
signalfx_tracing-2.2.0.dist-info/top_level.txt
signalfx_tracing-2.2.0.dist-info/RECORD
