Metadata-Version: 2.1
Name: signalfx-tracing
Version: 2.2.0
Summary: Provides auto-instrumentation for OpenTracing-traced libraries and frameworks
Home-page: http://github.com/signalfx/signalfx-python-tracing
Author: SignalFx
Author-email: signalfx-oss@splunk.com
License: Apache Software License v2
Download-URL: http://github.com/signalfx/signalfx-python-tracing/tarball/master
Platform: UNKNOWN
Classifier: Development Status :: 4 - Beta
Classifier: Intended Audience :: Developers
Classifier: Natural Language :: English
Classifier: License :: OSI Approved :: Apache Software License
Classifier: Programming Language :: Python
Classifier: Programming Language :: Python :: 2
Classifier: Programming Language :: Python :: 2.7
Classifier: Programming Language :: Python :: 3
Classifier: Programming Language :: Python :: 3.4
Classifier: Programming Language :: Python :: 3.5
Classifier: Programming Language :: Python :: 3.6
Classifier: Programming Language :: Python :: 3.7
Requires-Dist: opentracing (<2.4,>=2.1)
Requires-Dist: six (>=1.12.0)
Requires-Dist: wrapt
Provides-Extra: celery
Requires-Dist: signalfx-instrumentation-celery (>=1.0.0) ; extra == 'celery'
Provides-Extra: dbapi
Requires-Dist: signalfx-instrumentation-dbapi (>=1.0.0) ; extra == 'dbapi'
Provides-Extra: django
Requires-Dist: signalfx-instrumentation-django (>=1.2.0) ; extra == 'django'
Provides-Extra: elasticsearch
Requires-Dist: signalfx-instrumentation-elasticsearch (>=1.0.0) ; extra == 'elasticsearch'
Provides-Extra: flask
Requires-Dist: signalfx-instrumentation-flask (>=1.3.0) ; extra == 'flask'
Provides-Extra: instrumentation_tests
Requires-Dist: django ; extra == 'instrumentation_tests'
Requires-Dist: docker ; extra == 'instrumentation_tests'
Requires-Dist: elasticsearch ; extra == 'instrumentation_tests'
Requires-Dist: flask ; extra == 'instrumentation_tests'
Requires-Dist: flake8 ; extra == 'instrumentation_tests'
Requires-Dist: falcon (<3.0) ; extra == 'instrumentation_tests'
Requires-Dist: mock ; extra == 'instrumentation_tests'
Requires-Dist: mockupdb ; extra == 'instrumentation_tests'
Requires-Dist: psycopg2 ; extra == 'instrumentation_tests'
Requires-Dist: pymongo ; extra == 'instrumentation_tests'
Requires-Dist: pymysql ; extra == 'instrumentation_tests'
Requires-Dist: pytest ; extra == 'instrumentation_tests'
Requires-Dist: pytest-django ; extra == 'instrumentation_tests'
Requires-Dist: redis ; extra == 'instrumentation_tests'
Requires-Dist: requests ; extra == 'instrumentation_tests'
Requires-Dist: six ; extra == 'instrumentation_tests'
Requires-Dist: tornado ; extra == 'instrumentation_tests'
Requires-Dist: sfx-jaeger-client (>=3.13.1b0.dev6) ; extra == 'instrumentation_tests'
Requires-Dist: signalfx-instrumentation-celery (>=1.0.0) ; extra == 'instrumentation_tests'
Requires-Dist: signalfx-instrumentation-dbapi (>=1.0.0) ; extra == 'instrumentation_tests'
Requires-Dist: signalfx-instrumentation-django (>=1.2.0) ; extra == 'instrumentation_tests'
Requires-Dist: signalfx-instrumentation-elasticsearch (>=1.0.0) ; extra == 'instrumentation_tests'
Requires-Dist: signalfx-instrumentation-flask (>=1.3.0) ; extra == 'instrumentation_tests'
Requires-Dist: signalfx-instrumentation-pymongo (>=1.0.0) ; extra == 'instrumentation_tests'
Requires-Dist: signalfx-instrumentation-redis (>=1.0.0) ; extra == 'instrumentation_tests'
Requires-Dist: signalfx-instrumentation-requests (>=1.0.0) ; extra == 'instrumentation_tests'
Requires-Dist: signalfx-instrumentation-tornado (>=1.2.0) ; extra == 'instrumentation_tests'
Provides-Extra: jaeger
Requires-Dist: sfx-jaeger-client (>=3.13.1b0.dev6) ; extra == 'jaeger'
Provides-Extra: psycopg2
Requires-Dist: signalfx-instrumentation-dbapi (>=1.0.0) ; extra == 'psycopg2'
Provides-Extra: pymongo
Requires-Dist: signalfx-instrumentation-pymongo (>=1.0.0) ; extra == 'pymongo'
Provides-Extra: pymysql
Requires-Dist: signalfx-instrumentation-dbapi (>=1.0.0) ; extra == 'pymysql'
Provides-Extra: redis
Requires-Dist: signalfx-instrumentation-redis (>=1.0.0) ; extra == 'redis'
Provides-Extra: requests
Requires-Dist: signalfx-instrumentation-requests (>=1.0.0) ; extra == 'requests'
Provides-Extra: tornado
Requires-Dist: signalfx-instrumentation-tornado (>=1.2.0) ; extra == 'tornado'
Provides-Extra: unit_tests
Requires-Dist: mock ; extra == 'unit_tests'
Requires-Dist: pytest ; extra == 'unit_tests'
Requires-Dist: six ; extra == 'unit_tests'
Requires-Dist: sfx-jaeger-client ; extra == 'unit_tests'
